clickup_async-1.0.0.dist-info/licenses/LICENSE
models/__init__.py
models/attachment.py
models/base.py
models/checklist.py
models/comment.py
models/common.py
models/doc.py
models/folder.py
models/goal.py
models/guest.py
models/list.py
models/space.py
models/tag.py
models/task.py
models/time.py
models/user.py
models/view.py
models/webhook.py
models/workspace.py
clickup_async-1.0.0.dist-info/METADATA
clickup_async-1.0.0.dist-info/WHEEL
clickup_async-1.0.0.dist-info/top_level.txt
clickup_async-1.0.0.dist-info/RECORD
